st_pages/__init__.py
st_pages/emoji.json
st_pages/py.typed
st_pages-1.0.0.dist-info/LICENSE
st_pages-1.0.0.dist-info/METADATA
st_pages-1.0.0.dist-info/WHEEL
st_pages-1.0.0.dist-info/RECORD
